host_terminal_mcp/__init__.py
host_terminal_mcp/config.py
host_terminal_mcp/executor.py
host_terminal_mcp/http_server.py
host_terminal_mcp/server.py
host_terminal_mcp-0.2.0.dist-info/METADATA
host_terminal_mcp-0.2.0.dist-info/WHEEL
host_terminal_mcp-0.2.0.dist-info/entry_points.txt
host_terminal_mcp-0.2.0.dist-info/licenses/LICENSE
host_terminal_mcp-0.2.0.dist-info/RECORD
