Metadata-Version: 2.4
Name: host-terminal-mcp
Version: 0.2.0
Summary: MCP server for executing terminal commands on the host machine with configurable permissions
Author-email: Ankit <ankit.ag.in@gmail.com>
License-Expression: Apache-2.0
License-File: LICENSE
Keywords: claude,cowork,mcp,shell,terminal
Classifier: Development Status :: 4 - Beta
Classifier: Intended Audience :: Developers
Classifier: License :: OSI Approved :: Apache Software License
Classifier: Programming Language :: Python :: 3
Classifier: Programming Language :: Python :: 3.10
Classifier: Programming Language :: Python :: 3.11
Classifier: Programming Language :: Python :: 3.12
Requires-Python: >=3.10
Requires-Dist: mcp>=1.0.0
Requires-Dist: pydantic>=2.0
Requires-Dist: pyyaml>=6.0
Provides-Extra: dev
Requires-Dist: mypy>=1.0; extra == 'dev'
Requires-Dist: pytest-asyncio>=0.21; extra == 'dev'
Requires-Dist: pytest-cov>=4.0; extra == 'dev'
Requires-Dist: pytest>=7.0; extra == 'dev'
Requires-Dist: ruff>=0.4.0; extra == 'dev'
Provides-Extra: http
Requires-Dist: fastapi>=0.100.0; extra == 'http'
Requires-Dist: uvicorn>=0.20.0; extra == 'http'
